dadosAbertosSetorEletrico/__init__.py
dados_abertos_setor_eletrico-0.1.4.dist-info/licenses/LICENSE.txt
dados_abertos_setor_eletrico-0.1.4.dist-info/METADATA
dados_abertos_setor_eletrico-0.1.4.dist-info/WHEEL
dados_abertos_setor_eletrico-0.1.4.dist-info/top_level.txt
dados_abertos_setor_eletrico-0.1.4.dist-info/RECORD
