Metadata-Version: 2.4
Name: dados-abertos-setor-eletrico
Version: 0.1.4
Summary: Coleta e tratamento de dados públicos do setor elétrico brasileiro (ONS, CCEE e ANEEL).
Home-page: https://github.com/diegonerii/Dados-Abertos-Setor-Eletrico-Brasileiro
Author: Diego Neri
Author-email: diego.holanda.neri@gmail.com
Requires-Python: >=3.8
License-File: LICENSE.txt
Requires-Dist: requests
Requires-Dist: pandas
Dynamic: license-file
